wego_piper/__init__.py
wego_piper/packet_handler.py
wego_piper/port_handler.py
wego_piper-0.0.1.dist-info/licenses/LICENSE.txt
wego_piper-0.0.1.dist-info/METADATA
wego_piper-0.0.1.dist-info/WHEEL
wego_piper-0.0.1.dist-info/entry_points.txt
wego_piper-0.0.1.dist-info/top_level.txt
wego_piper-0.0.1.dist-info/RECORD
